{
  "document_id": "doc_1773764460_Group_01_URSSAF_20260317_163552",
  "filename": "Group_01_URSSAF_20260317_163552.pdf",
  "source_path": "/opt/airflow/data/incoming/Group_01_URSSAF_20260317_163552.pdf",
  "detected_type": "attestation",
  "status": "PENDING",
  "detected_at": "2026-03-17T16:21:00.070120",
  "raw_path": "/opt/airflow/data/raw/Group_01_URSSAF_20260317_163552.pdf",
  "gridfs_id": "69b97f6fb817e2e0a51b7ca2",
  "ingested_at": "2026-03-17T16:21:03.758073",
  "ocr_text_path": "/opt/airflow/data/clean/Group_01_URSSAF_20260317_163552.txt",
  "ocr_confidence": 0.91,
  "ocr_at": "2026-03-17T16:21:15.018188",
  "extracted_fields": {
    "amount_ht": null,
    "amount_ttc": null,
    "date_emission": "17/03/2026",
    "date_delivrance": null,
    "date_expiration": null,
    "siren": null,
    "siret": null,
    "tva": null,
    "tva_rate": null,
    "iban": null,
    "doc_type": "attestation",
    "extracted_raw": {
      "siret": null,
      "tva": null,
      "montant": [],
      "date": [
        "17/03/2026",
        "24/09/2026"
      ]
    }
  },
  "extraction_confidence": 0.87,
  "extracted_at": "2026-03-17T16:21:47.196888",
  "validation_alerts": [
    {
      "level": "warning",
      "message": "Attestation sans KBIS lié via SIRET/SIREN"
    }
  ],
  "validated_at": "2026-03-17T16:21:50.939675"
}